repro_apk/__init__.py
repro_apk/binres.py
repro_apk/diff_zip_meta.py
repro_apk/dump_arsc.py
repro_apk/dump_axml.py
repro_apk/dump_baseline.py
repro_apk/fix_compresslevel.py
repro_apk/fix_files.py
repro_apk/fix_newlines.py
repro_apk/fix_pg_map_id.py
repro_apk/inplace_fix.py
repro_apk/list_compresslevel.py
repro_apk/py.typed
repro_apk/rm_files.py
repro_apk/sort_apk.py
repro_apk/sort_baseline.py
repro_apk/zipalign.py
repro_apk/zipalignment.py
repro_apk/zipinfo.py
repro_apk-0.3.0.dist-info/LICENSE.AGPLv3
repro_apk-0.3.0.dist-info/METADATA
repro_apk-0.3.0.dist-info/WHEEL
repro_apk-0.3.0.dist-info/entry_points.txt
repro_apk-0.3.0.dist-info/top_level.txt
repro_apk-0.3.0.dist-info/RECORD
